morris_lee.py
morris_lee-0.1.dist-info/METADATA
morris_lee-0.1.dist-info/WHEEL
morris_lee-0.1.dist-info/top_level.txt
morris_lee-0.1.dist-info/RECORD
